{
  "anvil_cost": 1,
  "description": {
    "translate": "enchantment.minecraft.infinity"
  },
  "effects": {
    "minecraft:ammo_use": [
      {
        "effect": {
          "type": "minecraft:set",
          "value": 0.0
        },
        "requirements": {
          "condition": "minecraft:match_tool",
          "predicate": {
            "items": "minecraft:arrow"
          }
        }
      }
    ]
  },
  "max_cost": {
    "base": 2147483647,
    "per_level_above_first": 0
  },
  "max_level": 1,
  "min_cost": {
    "base": 14,
    "per_level_above_first": 0
  },
  "slots": [
    "mainhand"
  ],
  "supported_items": "#ogvz:enchantable/any_bow",
  "weight": 2
}